asteroloc8/__init__.py
asteroloc8/prior.py
asteroloc8/version.py
asteroloc8-0.0.1.dist-info/LICENSE
asteroloc8-0.0.1.dist-info/METADATA
asteroloc8-0.0.1.dist-info/WHEEL
asteroloc8-0.0.1.dist-info/top_level.txt
asteroloc8-0.0.1.dist-info/RECORD
