Metadata-Version: 2.1
Name: asteroloc8
Version: 0.0.1
Summary: Locate asteroseismic numax
Home-page: https://github.com/alexlyttle/asteroloc8
Author: Alex Lyttle, Joel Zinn, Ted Mackereth, Jamie Tayar, Martin Nielsen
License: MIT
Platform: UNKNOWN
Classifier: Programming Language :: Python :: 3
Classifier: License :: OSI Approved :: MIT License
Classifier: Operating System :: OS Independent
Requires-Python: >=3.6
Requires-Dist: numpy
Requires-Dist: scipy
Requires-Dist: astropy
Requires-Dist: tqdm
